odoo/addons/graphql_base/README.rst
odoo/addons/graphql_base/__init__.py
odoo/addons/graphql_base/__manifest__.py
odoo/addons/graphql_base/graphene_types.py
odoo/addons/graphql_base/controllers/__init__.py
odoo/addons/graphql_base/controllers/main.py
odoo/addons/graphql_base/i18n/graphql_base.pot
odoo/addons/graphql_base/i18n/it.po
odoo/addons/graphql_base/readme/DESCRIPTION.md
odoo/addons/graphql_base/readme/USAGE.md
odoo/addons/graphql_base/static/description/icon.png
odoo/addons/graphql_base/static/description/index.html
odoo/addons/graphql_base/views/graphiql.xml
odoo_addon_graphql_base-17.0.1.1.0.dist-info/METADATA
odoo_addon_graphql_base-17.0.1.1.0.dist-info/WHEEL
odoo_addon_graphql_base-17.0.1.1.0.dist-info/top_level.txt
odoo_addon_graphql_base-17.0.1.1.0.dist-info/RECORD
